[
    {
        "name": "La Theine Plateau",
        "category": "Base Game",
        "file_rom": "ROM\\0\\115.DAT",
        "file_id": 202,
        "rom_index": 1,
        "rom_folder": "ROM",
        "dat": "ROM\\0\\115.DAT",
        "dat_id": 115,
        "dat_dir": 0,
        "dat_path": 115,
        "dat_header": "f_la"
    },
    {
        "name": "West Ronfaure",
        "category": "Base Game",
        "file_rom": "ROM\\0\\120.DAT",
        "file_id": 200,
        "rom_index": 1,
        "rom_folder": "ROM",
        "dat": "ROM\\0\\120.DAT",
        "dat_id": 120,
        "dat_dir": 0,
        "dat_path": 120,
        "dat_header": "f_ro"
    },
    {
        "name": "East Ronfaure",
        "category": "Base Game",
        "file_rom": "ROM\\0\\121.DAT",
        "file_id": 201,
        "rom_index": 1,
        "rom_folder": "ROM",
        "dat": "ROM\\0\\121.DAT",
        "dat_id": 121,
        "dat_dir": 0,
        "dat_path": 121,
        "dat_header": "f_ro"
    },
    {
        "name": "King Ranperre's Tomb",
        "category": "Base Game",
        "file_rom": "ROM\\1\\14.DAT",
        "file_id": 290,
        "rom_index": 1,
        "rom_folder": "ROM",
        "dat": "ROM\\1\\14.DAT",
        "dat_id": 142,
        "dat_dir": 1,
        "dat_path": 14,
        "dat_header": "h_ro"
    },
    {
        "name": "North Gustaberg",
        "category": "Base Game",
        "file_rom": "ROM\\0\\123.DAT",
        "file_id": 206,
        "rom_index": 1,
        "rom_folder": "ROM",
        "dat": "ROM\\0\\123.DAT",
        "dat_id": 123,
        "dat_dir": 0,
        "dat_path": 123,
        "dat_header": "f_gu"
    },
    {
        "name": "South Gustaberg",
        "category": "Base Game",
        "file_rom": "ROM\\0\\124.DAT",
        "file_id": 207,
        "rom_index": 1,
        "rom_folder": "ROM",
        "dat": "ROM\\0\\124.DAT",
        "dat_id": 124,
        "dat_dir": 0,
        "dat_path": 124,
        "dat_header": "f_gu"
    },
    {
        "name": "West Sarutabaruta",
        "category": "Base Game",
        "file_rom": "ROM\\0\\127.DAT",
        "file_id": 215,
        "rom_index": 1,
        "rom_folder": "ROM",
        "dat": "ROM\\0\\127.DAT",
        "dat_id": 127,
        "dat_dir": 0,
        "dat_path": 127,
        "dat_header": "f_sa"
    },
    {
        "name": "East Sarutabaruta",
        "category": "Base Game",
        "file_rom": "ROM\\1\\0.DAT",
        "file_id": 216,
        "rom_index": 1,
        "rom_folder": "ROM",
        "dat": "ROM\\1\\0.DAT",
        "dat_id": 128,
        "dat_dir": 1,
        "dat_path": 0,
        "dat_header": "f_sa"
    },
    {
        "name": "Southern San d'Oria",
        "category": "Base Game",
        "file_rom": "ROM\\1\\31.DAT",
        "file_id": 330,
        "rom_index": 1,
        "rom_folder": "ROM",
        "dat": "ROM\\1\\31.DAT",
        "dat_id": 159,
        "dat_dir": 1,
        "dat_path": 31,
        "dat_header": "t_sa"
    },
    {
        "name": "Northern San d'Oria",
        "category": "Base Game",
        "file_rom": "ROM\\1\\32.DAT",
        "file_id": 331,
        "rom_index": 1,
        "rom_folder": "ROM",
        "dat": "ROM\\1\\32.DAT",
        "dat_id": 160,
        "dat_dir": 1,
        "dat_path": 32,
        "dat_header": "wt_s"
    },
    {
        "name": "Windurst Waters",
        "category": "Base Game",
        "file_rom": "ROM\\0\\78.DAT",
        "file_id": 338,
        "rom_index": 1,
        "rom_folder": "ROM",
        "dat": "ROM\\0\\78.DAT",
        "dat_id": 78,
        "dat_dir": 0,
        "dat_path": 78,
        "dat_header": "t_wi"
    },
    {
        "name": "Windurst Walls",
        "category": "Base Game",
        "file_rom": "ROM\\0\\79.DAT",
        "file_id": 339,
        "rom_index": 1,
        "rom_folder": "ROM",
        "dat": "ROM\\0\\79.DAT",
        "dat_id": 79,
        "dat_dir": 0,
        "dat_path": 79,
        "dat_header": "t_wi"
    },
    {
        "name": "Windurst Woods",
        "category": "Base Game",
        "file_rom": "ROM\\0\\81.DAT",
        "file_id": 341,
        "rom_index": 1,
        "rom_folder": "ROM",
        "dat": "ROM\\0\\81.DAT",
        "dat_id": 81,
        "dat_dir": 0,
        "dat_path": 81,
        "dat_header": "t_wi"
    },
    {
        "name": "Heavens Tower",
        "category": "Base Game",
        "file_rom": "ROM\\1\\38.DAT",
        "file_id": 342,
        "rom_index": 1,
        "rom_folder": "ROM",
        "dat": "ROM\\1\\38.DAT",
        "dat_id": 166,
        "dat_dir": 1,
        "dat_path": 38,
        "dat_header": "t_wi"
    },
    {
        "name": "Port Windurst",
        "category": "Base Game",
        "file_rom": "ROM\\0\\80.DAT",
        "file_id": 340,
        "rom_index": 1,
        "rom_folder": "ROM",
        "dat": "ROM\\0\\80.DAT",
        "dat_id": 80,
        "dat_dir": 0,
        "dat_path": 80,
        "dat_header": "t_wi"
    },
    {
        "name": "Bastok Mines",
        "category": "Base Game",
        "file_rom": "ROM\\1\\34.DAT",
        "file_id": 334,
        "rom_index": 1,
        "rom_folder": "ROM",
        "dat": "ROM\\1\\34.DAT",
        "dat_id": 162,
        "dat_dir": 1,
        "dat_path": 34,
        "dat_header": "t_ba"
    },
    {
        "name": "Bastok Markets",
        "category": "Base Game",
        "file_rom": "ROM\\1\\35.DAT",
        "file_id": 335,
        "rom_index": 1,
        "rom_folder": "ROM",
        "dat": "ROM\\1\\35.DAT",
        "dat_id": 163,
        "dat_dir": 1,
        "dat_path": 35,
        "dat_header": "t_ba"
    },
    {
        "name": "Port Bastok",
        "category": "Base Game",
        "file_rom": "ROM\\1\\36.DAT",
        "file_id": 336,
        "rom_index": 1,
        "rom_folder": "ROM",
        "dat": "ROM\\1\\36.DAT",
        "dat_id": 164,
        "dat_dir": 1,
        "dat_path": 36,
        "dat_header": "t_ba"
    },
    {
        "name": "Metalworks",
        "category": "Base Game",
        "file_rom": "ROM\\1\\37.DAT",
        "file_id": 337,
        "rom_index": 1,
        "rom_folder": "ROM",
        "dat": "ROM\\1\\37.DAT",
        "dat_id": 165,
        "dat_dir": 1,
        "dat_path": 37,
        "dat_header": "wt_b"
    },
    {
        "name": "Upper Jeuno",
        "category": "Base Game",
        "file_rom": "ROM\\1\\40.DAT",
        "file_id": 344,
        "rom_index": 1,
        "rom_folder": "ROM",
        "dat": "ROM\\1\\40.DAT",
        "dat_id": 168,
        "dat_dir": 1,
        "dat_path": 40,
        "dat_header": "t_ju"
    },
    {
        "name": "Lower Jeuno",
        "category": "Base Game",
        "file_rom": "ROM\\1\\41.DAT",
        "file_id": 345,
        "rom_index": 1,
        "rom_folder": "ROM",
        "dat": "ROM\\1\\41.DAT",
        "dat_id": 169,
        "dat_dir": 1,
        "dat_path": 41,
        "dat_header": "t_ju"
    },
    {
        "name": "Port Jeuno",
        "category": "Base Game",
        "file_rom": "ROM\\1\\42.DAT",
        "file_id": 346,
        "rom_index": 1,
        "rom_folder": "ROM",
        "dat": "ROM\\1\\42.DAT",
        "dat_id": 170,
        "dat_dir": 1,
        "dat_path": 42,
        "dat_header": "t_ju"
    },
    {
        "name": "Ru'Lude Gardens",
        "category": "Base Game",
        "file_rom": "ROM\\1\\39.DAT",
        "file_id": 343,
        "rom_index": 1,
        "rom_folder": "ROM",
        "dat": "ROM\\1\\39.DAT",
        "dat_id": 167,
        "dat_dir": 1,
        "dat_path": 39,
        "dat_header": "t_ju"
    },
    {
        "name": "Qufim Island",
        "category": "Base Game",
        "file_rom": "ROM\\0\\58.DAT",
        "file_id": 226,
        "rom_index": 1,
        "rom_folder": "ROM",
        "dat": "ROM\\0\\58.DAT",
        "dat_id": 58,
        "dat_dir": 0,
        "dat_path": 58,
        "dat_header": "f_qu"
    },
    {
        "name": "Ship bound for Selbina",
        "category": "Base Game",
        "file_rom": "ROM\\1\\24.DAT",
        "file_id": 320,
        "rom_index": 1,
        "rom_folder": "ROM",
        "dat": "ROM\\1\\24.DAT",
        "dat_id": 152,
        "dat_dir": 1,
        "dat_path": 24,
        "dat_header": "s_ba"
    },
    {
        "name": "Ship bound for Mhaura",
        "category": "Base Game",
        "file_rom": "ROM\\1\\25.DAT",
        "file_id": 321,
        "rom_index": 1,
        "rom_folder": "ROM",
        "dat": "ROM\\1\\25.DAT",
        "dat_id": 153,
        "dat_dir": 1,
        "dat_path": 25,
        "dat_header": "s_ba"
    },
    {
        "name": "Ship bound for Selbina",
        "category": "Base Game",
        "file_rom": "ROM\\1\\29.DAT",
        "file_id": 327,
        "rom_index": 1,
        "rom_folder": "ROM",
        "dat": "ROM\\1\\29.DAT",
        "dat_id": 157,
        "dat_dir": 1,
        "dat_path": 29,
        "dat_header": "s_ba"
    },
    {
        "name": "Ship bound for Mhaura",
        "category": "Base Game",
        "file_rom": "ROM\\1\\30.DAT",
        "file_id": 328,
        "rom_index": 1,
        "rom_folder": "ROM",
        "dat": "ROM\\1\\30.DAT",
        "dat_id": 158,
        "dat_dir": 1,
        "dat_path": 30,
        "dat_header": "s_ba"
    },
    {
        "name": "San d'Oria-Jeuno Airship",
        "category": "Base Game",
        "file_rom": "ROM\\1\\26.DAT",
        "file_id": 323,
        "rom_index": 1,
        "rom_folder": "ROM",
        "dat": "ROM\\1\\26.DAT",
        "dat_id": 154,
        "dat_dir": 1,
        "dat_path": 26,
        "dat_header": "s_em"
    },
    {
        "name": "Bastok-Jeuno Airship",
        "category": "Base Game",
        "file_rom": "ROM\\1\\27.DAT",
        "file_id": 324,
        "rom_index": 1,
        "rom_folder": "ROM",
        "dat": "ROM\\1\\27.DAT",
        "dat_id": 155,
        "dat_dir": 1,
        "dat_path": 27,
        "dat_header": "s_em"
    },
    {
        "name": "Windurst-Jeuno Airship",
        "category": "Base Game",
        "file_rom": "ROM\\1\\28.DAT",
        "file_id": 325,
        "rom_index": 1,
        "rom_folder": "ROM",
        "dat": "ROM\\1\\28.DAT",
        "dat_id": 156,
        "dat_dir": 1,
        "dat_path": 28,
        "dat_header": "s_em"
    },
    {
        "name": "Tahrongi Canyon",
        "category": "Base Game",
        "file_rom": "ROM\\1\\1.DAT",
        "file_id": 217,
        "rom_index": 1,
        "rom_folder": "ROM",
        "dat": "ROM\\1\\1.DAT",
        "dat_id": 129,
        "dat_dir": 1,
        "dat_path": 1,
        "dat_header": "f_el"
    },
    {
        "name": "Valkurm Dunes",
        "category": "Base Game",
        "file_rom": "ROM\\0\\102.DAT",
        "file_id": 203,
        "rom_index": 1,
        "rom_folder": "ROM",
        "dat": "ROM\\0\\102.DAT",
        "dat_id": 102,
        "dat_dir": 0,
        "dat_path": 102,
        "dat_header": "f_ki"
    },
    {
        "name": "Jugner Forest",
        "category": "Base Game",
        "file_rom": "ROM\\0\\114.DAT",
        "file_id": 204,
        "rom_index": 1,
        "rom_folder": "ROM",
        "dat": "ROM\\0\\114.DAT",
        "dat_id": 114,
        "dat_dir": 0,
        "dat_path": 114,
        "dat_header": "f_ju"
    },
    {
        "name": "Batallia Downs",
        "category": "Base Game",
        "file_rom": "ROM\\0\\122.DAT",
        "file_id": 205,
        "rom_index": 1,
        "rom_folder": "ROM",
        "dat": "ROM\\0\\122.DAT",
        "dat_id": 122,
        "dat_dir": 0,
        "dat_path": 122,
        "dat_header": "f_no"
    },
    {
        "name": "Konschtat Highlands",
        "category": "Base Game",
        "file_rom": "ROM\\0\\90.DAT",
        "file_id": 208,
        "rom_index": 1,
        "rom_folder": "ROM",
        "dat": "ROM\\0\\90.DAT",
        "dat_id": 90,
        "dat_dir": 0,
        "dat_path": 90,
        "dat_header": "f_ko"
    },
    {
        "name": "Pashhow Marshlands",
        "category": "Base Game",
        "file_rom": "ROM\\0\\125.DAT",
        "file_id": 209,
        "rom_index": 1,
        "rom_folder": "ROM",
        "dat": "ROM\\0\\125.DAT",
        "dat_id": 125,
        "dat_dir": 0,
        "dat_path": 125,
        "dat_header": "f_or"
    },
    {
        "name": "Rolanberry Fields",
        "category": "Base Game",
        "file_rom": "ROM\\0\\126.DAT",
        "file_id": 210,
        "rom_index": 1,
        "rom_folder": "ROM",
        "dat": "ROM\\0\\126.DAT",
        "dat_id": 126,
        "dat_dir": 0,
        "dat_path": 126,
        "dat_header": "f_ro"
    },
    {
        "name": "Beaucedine Glacier",
        "category": "Base Game",
        "file_rom": "ROM\\0\\72.DAT",
        "file_id": 211,
        "rom_index": 1,
        "rom_folder": "ROM",
        "dat": "ROM\\0\\72.DAT",
        "dat_id": 72,
        "dat_dir": 0,
        "dat_path": 72,
        "dat_header": "f_ga"
    },
    {
        "name": "Xarcabard",
        "category": "Base Game",
        "file_rom": "ROM\\0\\57.DAT",
        "file_id": 212,
        "rom_index": 1,
        "rom_folder": "ROM",
        "dat": "ROM\\0\\57.DAT",
        "dat_id": 57,
        "dat_dir": 0,
        "dat_path": 57,
        "dat_header": "f_xa"
    },
    {
        "name": "Buburimu Peninsula",
        "category": "Base Game",
        "file_rom": "ROM\\0\\71.DAT",
        "file_id": 218,
        "rom_index": 1,
        "rom_folder": "ROM",
        "dat": "ROM\\0\\71.DAT",
        "dat_id": 71,
        "dat_dir": 0,
        "dat_path": 71,
        "dat_header": "f_pa"
    },
    {
        "name": "Meriphataud Mountains",
        "category": "Base Game",
        "file_rom": "ROM\\0\\101.DAT",
        "file_id": 219,
        "rom_index": 1,
        "rom_folder": "ROM",
        "dat": "ROM\\0\\101.DAT",
        "dat_id": 101,
        "dat_dir": 0,
        "dat_path": 101,
        "dat_header": "f_me"
    },
    {
        "name": "Sauromugue Champaign",
        "category": "Base Game",
        "file_rom": "ROM\\1\\2.DAT",
        "file_id": 220,
        "rom_index": 1,
        "rom_folder": "ROM",
        "dat": "ROM\\1\\2.DAT",
        "dat_id": 130,
        "dat_dir": 1,
        "dat_path": 2,
        "dat_header": "f_al"
    },
    {
        "name": "Behemoth's Dominion",
        "category": "Base Game",
        "file_rom": "ROM\\1\\3.DAT",
        "file_id": 227,
        "rom_index": 1,
        "rom_folder": "ROM",
        "dat": "ROM\\1\\3.DAT",
        "dat_id": 131,
        "dat_dir": 1,
        "dat_path": 3,
        "dat_header": "f_qu"
    },
    {
        "name": "Mordion Gaol",
        "category": "Base Game",
        "file_rom": "ROM\\1\\4.DAT",
        "file_id": 231,
        "rom_index": 1,
        "rom_folder": "ROM",
        "dat": "ROM\\1\\4.DAT",
        "dat_id": 132,
        "dat_dir": 1,
        "dat_path": 4,
        "dat_header": "j_ai"
    },
    {
        "name": "Horlais Peak",
        "category": "Base Game",
        "file_rom": "ROM\\1\\6.DAT",
        "file_id": 239,
        "rom_index": 1,
        "rom_folder": "ROM",
        "dat": "ROM\\1\\6.DAT",
        "dat_id": 134,
        "dat_dir": 1,
        "dat_path": 6,
        "dat_header": "d_gh"
    },
    {
        "name": "Ghelsba Outpost",
        "category": "Base Game",
        "file_rom": "ROM\\0\\95.DAT",
        "file_id": 240,
        "rom_index": 1,
        "rom_folder": "ROM",
        "dat": "ROM\\0\\95.DAT",
        "dat_id": 95,
        "dat_dir": 0,
        "dat_path": 95,
        "dat_header": "d_gh"
    },
    {
        "name": "Fort Ghelsba",
        "category": "Base Game",
        "file_rom": "ROM\\1\\7.DAT",
        "file_id": 241,
        "rom_index": 1,
        "rom_folder": "ROM",
        "dat": "ROM\\1\\7.DAT",
        "dat_id": 135,
        "dat_dir": 1,
        "dat_path": 7,
        "dat_header": "d_gh"
    },
    {
        "name": "Yughott Grotto",
        "category": "Base Game",
        "file_rom": "ROM\\1\\8.DAT",
        "file_id": 242,
        "rom_index": 1,
        "rom_folder": "ROM",
        "dat": "ROM\\1\\8.DAT",
        "dat_id": 136,
        "dat_dir": 1,
        "dat_path": 8,
        "dat_header": "d_gh"
    },
    {
        "name": "Palborough Mines",
        "category": "Base Game",
        "file_rom": "ROM\\0\\88.DAT",
        "file_id": 243,
        "rom_index": 1,
        "rom_folder": "ROM",
        "dat": "ROM\\0\\88.DAT",
        "dat_id": 88,
        "dat_dir": 0,
        "dat_path": 88,
        "dat_header": "d_pa"
    },
    {
        "name": "Waughroon Shrine",
        "category": "Base Game",
        "file_rom": "ROM\\0\\89.DAT",
        "file_id": 244,
        "rom_index": 1,
        "rom_folder": "ROM",
        "dat": "ROM\\0\\89.DAT",
        "dat_id": 89,
        "dat_dir": 0,
        "dat_path": 89,
        "dat_header": "d_pa"
    },
    {
        "name": "Giddeus",
        "category": "Base Game",
        "file_rom": "ROM\\0\\104.DAT",
        "file_id": 245,
        "rom_index": 1,
        "rom_folder": "ROM",
        "dat": "ROM\\0\\104.DAT",
        "dat_id": 104,
        "dat_dir": 0,
        "dat_path": 104,
        "dat_header": "d_gi"
    },
    {
        "name": "Balga's Dais",
        "category": "Base Game",
        "file_rom": "ROM\\0\\105.DAT",
        "file_id": 246,
        "rom_index": 1,
        "rom_folder": "ROM",
        "dat": "ROM\\0\\105.DAT",
        "dat_id": 105,
        "dat_dir": 0,
        "dat_path": 105,
        "dat_header": "d_gi"
    },
    {
        "name": "Beadeaux",
        "category": "Base Game",
        "file_rom": "ROM\\0\\61.DAT",
        "file_id": 247,
        "rom_index": 1,
        "rom_folder": "ROM",
        "dat": "ROM\\0\\61.DAT",
        "dat_id": 61,
        "dat_dir": 0,
        "dat_path": 61,
        "dat_header": "d_be"
    },
    {
        "name": "Qulun Dome",
        "category": "Base Game",
        "file_rom": "ROM\\0\\62.DAT",
        "file_id": 248,
        "rom_index": 1,
        "rom_folder": "ROM",
        "dat": "ROM\\0\\62.DAT",
        "dat_id": 62,
        "dat_dir": 0,
        "dat_path": 62,
        "dat_header": "d_be"
    },
    {
        "name": "Davoi",
        "category": "Base Game",
        "file_rom": "ROM\\0\\99.DAT",
        "file_id": 249,
        "rom_index": 1,
        "rom_folder": "ROM",
        "dat": "ROM\\0\\99.DAT",
        "dat_id": 99,
        "dat_dir": 0,
        "dat_path": 99,
        "dat_header": "d_da"
    },
    {
        "name": "Monastic Cavern",
        "category": "Base Game",
        "file_rom": "ROM\\0\\100.DAT",
        "file_id": 250,
        "rom_index": 1,
        "rom_folder": "ROM",
        "dat": "ROM\\0\\100.DAT",
        "dat_id": 100,
        "dat_dir": 0,
        "dat_path": 100,
        "dat_header": "d_da"
    },
    {
        "name": "Castle Oztroja",
        "category": "Base Game",
        "file_rom": "ROM\\0\\63.DAT",
        "file_id": 251,
        "rom_index": 1,
        "rom_folder": "ROM",
        "dat": "ROM\\0\\63.DAT",
        "dat_id": 63,
        "dat_dir": 0,
        "dat_path": 63,
        "dat_header": "d_oz"
    },
    {
        "name": "Altar Room",
        "category": "Base Game",
        "file_rom": "ROM\\0\\64.DAT",
        "file_id": 252,
        "rom_index": 1,
        "rom_folder": "ROM",
        "dat": "ROM\\0\\64.DAT",
        "dat_id": 64,
        "dat_dir": 0,
        "dat_path": 64,
        "dat_header": "d_oz"
    },
    {
        "name": "Middle Delkfutt's Tower",
        "category": "Base Game",
        "file_rom": "ROM\\0\\56.DAT",
        "file_id": 257,
        "rom_index": 1,
        "rom_folder": "ROM",
        "dat": "ROM\\0\\56.DAT",
        "dat_id": 56,
        "dat_dir": 0,
        "dat_path": 56,
        "dat_header": "d_de"
    },
    {
        "name": "Upper Delkfutt's Tower",
        "category": "Base Game",
        "file_rom": "ROM\\1\\9.DAT",
        "file_id": 258,
        "rom_index": 1,
        "rom_folder": "ROM",
        "dat": "ROM\\1\\9.DAT",
        "dat_id": 137,
        "dat_dir": 1,
        "dat_path": 9,
        "dat_header": "d_de"
    },
    {
        "name": "Lower Delkfutt's Tower",
        "category": "Base Game",
        "file_rom": "ROM\\1\\13.DAT",
        "file_id": 284,
        "rom_index": 1,
        "rom_folder": "ROM",
        "dat": "ROM\\1\\13.DAT",
        "dat_id": 141,
        "dat_dir": 1,
        "dat_path": 13,
        "dat_header": "d_de"
    },
    {
        "name": "Castle Zvahl Baileys",
        "category": "Base Game",
        "file_rom": "ROM\\0\\60.DAT",
        "file_id": 261,
        "rom_index": 1,
        "rom_folder": "ROM",
        "dat": "ROM\\0\\60.DAT",
        "dat_id": 60,
        "dat_dir": 0,
        "dat_path": 60,
        "dat_header": "d_zv"
    },
    {
        "name": "Castle Zvahl Keep",
        "category": "Base Game",
        "file_rom": "ROM\\0\\73.DAT",
        "file_id": 262,
        "rom_index": 1,
        "rom_folder": "ROM",
        "dat": "ROM\\0\\73.DAT",
        "dat_id": 73,
        "dat_dir": 0,
        "dat_path": 73,
        "dat_header": "d_zv"
    },
    {
        "name": "Throne Room",
        "category": "Base Game",
        "file_rom": "ROM\\0\\74.DAT",
        "file_id": 265,
        "rom_index": 1,
        "rom_folder": "ROM",
        "dat": "ROM\\0\\74.DAT",
        "dat_id": 74,
        "dat_dir": 0,
        "dat_path": 74,
        "dat_header": "d_zv"
    },
    {
        "name": "Ranguemont Pass",
        "category": "Base Game",
        "file_rom": "ROM\\1\\10.DAT",
        "file_id": 266,
        "rom_index": 1,
        "rom_folder": "ROM",
        "dat": "ROM\\1\\10.DAT",
        "dat_id": 138,
        "dat_dir": 1,
        "dat_path": 10,
        "dat_header": "d_sa"
    },
    {
        "name": "Bostaunieux Oubliette",
        "category": "Base Game",
        "file_rom": "ROM\\0\\108.DAT",
        "file_id": 267,
        "rom_index": 1,
        "rom_folder": "ROM",
        "dat": "ROM\\0\\108.DAT",
        "dat_id": 108,
        "dat_dir": 0,
        "dat_path": 108,
        "dat_header": "d_sa"
    },
    {
        "name": "Toraimarai Canal",
        "category": "Base Game",
        "file_rom": "ROM\\0\\65.DAT",
        "file_id": 269,
        "rom_index": 1,
        "rom_folder": "ROM",
        "dat": "ROM\\0\\65.DAT",
        "dat_id": 65,
        "dat_dir": 0,
        "dat_path": 65,
        "dat_header": "d_wi"
    },
    {
        "name": "Zeruhn Mines",
        "category": "Base Game",
        "file_rom": "ROM\\1\\11.DAT",
        "file_id": 272,
        "rom_index": 1,
        "rom_folder": "ROM",
        "dat": "ROM\\1\\11.DAT",
        "dat_id": 139,
        "dat_dir": 1,
        "dat_path": 11,
        "dat_header": "d_co"
    },
    {
        "name": "Maquette Abdhaljs-Legion",
        "category": "Base Game",
        "file_rom": "ROM\\1\\12.DAT",
        "file_id": 283,
        "rom_index": 1,
        "rom_folder": "ROM",
        "dat": "ROM\\1\\12.DAT",
        "dat_id": 140,
        "dat_dir": 1,
        "dat_path": 12,
        "dat_header": "d_wl"
    },
    {
        "name": "Inner Horutoto Ruins",
        "category": "Base Game",
        "file_rom": "ROM\\0\\112.DAT",
        "file_id": 292,
        "rom_index": 1,
        "rom_folder": "ROM",
        "dat": "ROM\\0\\112.DAT",
        "dat_id": 112,
        "dat_dir": 0,
        "dat_path": 112,
        "dat_header": "h_sa"
    },
    {
        "name": "Outer Horutoto Ruins",
        "category": "Base Game",
        "file_rom": "ROM\\1\\15.DAT",
        "file_id": 294,
        "rom_index": 1,
        "rom_folder": "ROM",
        "dat": "ROM\\1\\15.DAT",
        "dat_id": 143,
        "dat_dir": 1,
        "dat_path": 15,
        "dat_header": "h_sa"
    },
    {
        "name": "Dangruf Wadi",
        "category": "Base Game",
        "file_rom": "ROM\\0\\52.DAT",
        "file_id": 291,
        "rom_index": 1,
        "rom_folder": "ROM",
        "dat": "ROM\\0\\52.DAT",
        "dat_id": 52,
        "dat_dir": 0,
        "dat_path": 52,
        "dat_header": "h_gu"
    },
    {
        "name": "Ordelle's Caves",
        "category": "Base Game",
        "file_rom": "ROM\\0\\92.DAT",
        "file_id": 293,
        "rom_index": 1,
        "rom_folder": "ROM",
        "dat": "ROM\\0\\92.DAT",
        "dat_id": 92,
        "dat_dir": 0,
        "dat_path": 92,
        "dat_header": "h_la"
    },
    {
        "name": "The Eldieme Necropolis",
        "category": "Base Game",
        "file_rom": "ROM\\0\\77.DAT",
        "file_id": 295,
        "rom_index": 1,
        "rom_folder": "ROM",
        "dat": "ROM\\0\\77.DAT",
        "dat_id": 77,
        "dat_dir": 0,
        "dat_path": 77,
        "dat_header": "h_no"
    },
    {
        "name": "Gusgen Mines",
        "category": "Base Game",
        "file_rom": "ROM\\1\\16.DAT",
        "file_id": 296,
        "rom_index": 1,
        "rom_folder": "ROM",
        "dat": "ROM\\1\\16.DAT",
        "dat_id": 144,
        "dat_dir": 1,
        "dat_path": 16,
        "dat_header": "h_ko"
    },
    {
        "name": "Crawlers' Nest",
        "category": "Base Game",
        "file_rom": "ROM\\0\\76.DAT",
        "file_id": 297,
        "rom_index": 1,
        "rom_folder": "ROM",
        "dat": "ROM\\0\\76.DAT",
        "dat_id": 76,
        "dat_dir": 0,
        "dat_path": 76,
        "dat_header": "h_ro"
    },
    {
        "name": "Maze of Shakhrami",
        "category": "Base Game",
        "file_rom": "ROM\\0\\75.DAT",
        "file_id": 298,
        "rom_index": 1,
        "rom_folder": "ROM",
        "dat": "ROM\\0\\75.DAT",
        "dat_id": 75,
        "dat_dir": 0,
        "dat_path": 75,
        "dat_header": "h_el"
    },
    {
        "name": "Garlaige Citadel",
        "category": "Base Game",
        "file_rom": "ROM\\1\\17.DAT",
        "file_id": 300,
        "rom_index": 1,
        "rom_folder": "ROM",
        "dat": "ROM\\1\\17.DAT",
        "dat_id": 145,
        "dat_dir": 1,
        "dat_path": 17,
        "dat_header": "h_al"
    },
    {
        "name": "Fei'Yin",
        "category": "Base Game",
        "file_rom": "ROM\\1\\18.DAT",
        "file_id": 304,
        "rom_index": 1,
        "rom_folder": "ROM",
        "dat": "ROM\\1\\18.DAT",
        "dat_id": 146,
        "dat_dir": 1,
        "dat_path": 18,
        "dat_header": "h_ga"
    },
    {
        "name": "Qu'Bia Arena",
        "category": "Base Game",
        "file_rom": "ROM\\1\\19.DAT",
        "file_id": 306,
        "rom_index": 1,
        "rom_folder": "ROM",
        "dat": "ROM\\1\\19.DAT",
        "dat_id": 147,
        "dat_dir": 1,
        "dat_path": 19,
        "dat_header": "h_ga"
    },
    {
        "name": "Provenance",
        "category": "Base Game",
        "file_rom": "ROM\\280\\2.DAT",
        "file_id": 322,
        "rom_index": 1,
        "rom_folder": "ROM",
        "dat": "ROM\\280\\2.DAT",
        "dat_id": 35842,
        "dat_dir": 280,
        "dat_path": 2,
        "dat_header": "d_at"
    },
    {
        "name": "Port San d'Oria",
        "category": "Base Game",
        "file_rom": "ROM\\0\\113.DAT",
        "file_id": 332,
        "rom_index": 1,
        "rom_folder": "ROM",
        "dat": "ROM\\0\\113.DAT",
        "dat_id": 113,
        "dat_dir": 0,
        "dat_path": 113,
        "dat_header": "t_sa"
    },
    {
        "name": "Chateau d'Oraguille",
        "category": "Base Game",
        "file_rom": "ROM\\1\\33.DAT",
        "file_id": 333,
        "rom_index": 1,
        "rom_folder": "ROM",
        "dat": "ROM\\1\\33.DAT",
        "dat_id": 161,
        "dat_dir": 1,
        "dat_path": 33,
        "dat_header": "t_sa"
    },
    {
        "name": "Selbina",
        "category": "Base Game",
        "file_rom": "ROM\\1\\43.DAT",
        "file_id": 348,
        "rom_index": 1,
        "rom_folder": "ROM",
        "dat": "ROM\\1\\43.DAT",
        "dat_id": 171,
        "dat_dir": 1,
        "dat_path": 43,
        "dat_header": "t_se"
    },
    {
        "name": "Mhaura",
        "category": "Base Game",
        "file_rom": "ROM\\1\\44.DAT",
        "file_id": 349,
        "rom_index": 1,
        "rom_folder": "ROM",
        "dat": "ROM\\1\\44.DAT",
        "dat_id": 172,
        "dat_dir": 1,
        "dat_path": 44,
        "dat_header": "t_ma"
    }
]